quark_devices_dwave/__init__.py
quark_devices_dwave/simulated_annealer.py
quark_devices_dwave-0.1.dist-info/METADATA
quark_devices_dwave-0.1.dist-info/WHEEL
quark_devices_dwave-0.1.dist-info/top_level.txt
quark_devices_dwave-0.1.dist-info/RECORD
